pytest_slow_first.py
pytest_slow_first-1.0.3.dist-info/LICENSE
pytest_slow_first-1.0.3.dist-info/METADATA
pytest_slow_first-1.0.3.dist-info/WHEEL
pytest_slow_first-1.0.3.dist-info/entry_points.txt
pytest_slow_first-1.0.3.dist-info/top_level.txt
pytest_slow_first-1.0.3.dist-info/RECORD
