Metadata-Version: 2.1
Name: pytest-slow-first
Version: 1.0.3
Summary: Prioritize running the slowest tests first.
Home-page: https://github.com/joaovitorsilvestre/pytest-slow-first
Author: João Vitor Silvestre
Author-email: joao_vitor_silvestre@outlook.com
Maintainer: João Vitor Silvestre
Maintainer-email: joao_vitor_silvestre@outlook.com
License: MIT
Classifier: Development Status :: 4 - Beta
Classifier: Framework :: Pytest
Classifier: Intended Audience :: Developers
Classifier: Topic :: Software Development :: Testing
Classifier: Programming Language :: Python
Classifier: Programming Language :: Python :: 3
Classifier: Programming Language :: Python :: 3.5
Classifier: Programming Language :: Python :: 3.6
Classifier: Programming Language :: Python :: 3.7
Classifier: Programming Language :: Python :: 3.8
Classifier: Programming Language :: Python :: 3.9
Classifier: Programming Language :: Python :: 3.10
Classifier: Programming Language :: Python :: 3.11
Classifier: Programming Language :: Python :: 3 :: Only
Classifier: Programming Language :: Python :: Implementation :: CPython
Classifier: Programming Language :: Python :: Implementation :: PyPy
Classifier: Operating System :: OS Independent
Classifier: License :: OSI Approved :: MIT License
Requires-Python: >=3.5
License-File: LICENSE
Requires-Dist: pytest >=3.5.0
